mapicx/Activation_function.py
mapicx/Data.py
mapicx/Loss_function.py
mapicx/Main.py
mapicx/Mapicx.py
mapicx/__init__.py
mapicx/interface.py
mapicx/layer.py
mapicx/neuron.py
mapicx/optimizers.py
mapicx-0.1.0.dist-info/METADATA
mapicx-0.1.0.dist-info/WHEEL
mapicx-0.1.0.dist-info/top_level.txt
mapicx-0.1.0.dist-info/RECORD
